Metadata-Version: 2.1
Name: tabpy
Version: 2.6.0
Summary: Web server Tableau uses to run Python scripts.
Home-page: https://github.com/tableau/TabPy
Download-URL: https://pypi.org/project/tabpy
Author: Tableau
Author-email: github@tableau.com
Maintainer: Tableau
Maintainer-email: github@tableau.com
License: MIT
Project-URL: Bug Tracker, https://github.com/tableau/TabPy/issues
Project-URL: Documentation, https://tableau.github.io/TabPy/
Project-URL: Source Code, https://github.com/tableau/TabPy
Keywords: tabpy tableau
Platform: Windows
Platform: Linux
Platform: Mac OS-X
Platform: Unix
Classifier: Development Status :: 5 - Production/Stable
Classifier: Intended Audience :: Developers
Classifier: Intended Audience :: Science/Research
Classifier: License :: OSI Approved :: MIT License
Classifier: Programming Language :: Python :: 3.7
Classifier: Programming Language :: Python :: 3.8
Classifier: Programming Language :: Python :: 3.9
Classifier: Topic :: Scientific/Engineering
Classifier: Topic :: Scientific/Engineering :: Information Analysis
Classifier: Operating System :: Microsoft :: Windows
Classifier: Operating System :: POSIX
Classifier: Operating System :: Unix
Classifier: Operating System :: MacOS
Requires-Python: >=3.7
License-File: LICENSE
Requires-Dist: cloudpickle
Requires-Dist: configparser
Requires-Dist: coverage
Requires-Dist: coveralls
Requires-Dist: docopt
Requires-Dist: future
Requires-Dist: genson
Requires-Dist: hypothesis
Requires-Dist: jsonschema
Requires-Dist: mock
Requires-Dist: nltk
Requires-Dist: numpy
Requires-Dist: pandas
Requires-Dist: pyopenssl
Requires-Dist: pytest
Requires-Dist: pytest-cov
Requires-Dist: requests
Requires-Dist: scipy
Requires-Dist: simplejson
Requires-Dist: scikit-learn
Requires-Dist: textblob
Requires-Dist: tornado
Requires-Dist: twisted
Requires-Dist: urllib3
